odd_even/__init__.py
odd_even/core.py
odd_even_kris-1.0.0.dist-info/METADATA
odd_even_kris-1.0.0.dist-info/WHEEL
odd_even_kris-1.0.0.dist-info/top_level.txt
odd_even_kris-1.0.0.dist-info/RECORD
