Metadata-Version: 2.4
Name: odd-even-kris
Version: 1.0.0
Summary: A lightweight odd-even utility toolkit
Author: Kris B
License: MIT
Project-URL: Homepage, https://pypi.org/project/odd-even-kris/
Classifier: Programming Language :: Python :: 3
Classifier: Operating System :: OS Independent
Requires-Python: >=3.7
